LICENSE
MANIFEST.in
README.rst
buildout.cfg
evaluate_scores.sh
miniconda.sh
plot_pad_diff_methods.sh
project_on_gmms.sh
requirements.txt
setup.py
train_gmms.sh
version.txt
bob/__init__.py
bob.paper.interspeech_2016.egg-info/PKG-INFO
bob.paper.interspeech_2016.egg-info/SOURCES.txt
bob.paper.interspeech_2016.egg-info/dependency_links.txt
bob.paper.interspeech_2016.egg-info/entry_points.txt
bob.paper.interspeech_2016.egg-info/requires.txt
bob.paper.interspeech_2016.egg-info/top_level.txt
bob/paper/__init__.py
bob/paper/interspeech_2016/__init__.py
bob/paper/interspeech_2016/scripts/__init__.py
bob/paper/interspeech_2016/scripts/pad_diff_sys_scores.py
bob/paper/interspeech_2016/scripts/pad_process_scores.py
bob/paper/interspeech_2016/scripts/pad_stats_summary.py
doc/conf.py
doc/index.rst