Metadata-Version: 1.1
Name: bob.paper.interspeech-2016
Version: 1.0.12
Summary: Cross-database evaluation of audio-based spoofing detection systems
Home-page: https://gitlab.idiap.ch/bob/bob.paper.interspeech_2016
Author: Pavel Korshunov
Author-email: pavel.korshunov@idiap.ch
License: BSD
Keywords: PAD experiments,paper package,cross-database testing
Platform: UNKNOWN
Classifier: Framework :: Bob
Classifier: Development Status :: 4 - Beta
Classifier: Intended Audience :: Science/Research
Classifier: License :: OSI Approved :: BSD License
Classifier: Natural Language :: English
Classifier: Programming Language :: Python
Classifier: Programming Language :: Python :: 3
Classifier: Topic :: Scientific/Engineering :: Artificial Intelligence
Classifier: Topic :: Database :: Front-Ends
